CHANGES.rst
LICENSE
MANIFEST.in
README.rst
knot.py
setup.py
test_knot.py
knot.egg-info/PKG-INFO
knot.egg-info/SOURCES.txt
knot.egg-info/dependency_links.txt
knot.egg-info/top_level.txt