Metadata-Version: 1.1
Name: knot
Version: 0.4.0
Summary: A small do-it-yourself dependency container.
Home-page: https://github.com/jaapverloop/knot
Author: Jaap Verloop
Author-email: j.verloop@gmail.com
License: MIT
Download-URL: https://github.com/jaapverloop/knot/tarball/0.3.0
Keywords: dependency,container
Platform: UNKNOWN
Classifier: Intended Audience :: Developers
Classifier: License :: OSI Approved :: MIT License
Classifier: Operating System :: OS Independent
Classifier: Programming Language :: Python
Classifier: Programming Language :: Python :: 2
Classifier: Programming Language :: Python :: 2.6
Classifier: Programming Language :: Python :: 2.7
Classifier: Programming Language :: Python :: 3
Classifier: Programming Language :: Python :: 3.3
Classifier: Programming Language :: Python :: 3.4
Classifier: Programming Language :: Python :: 3.5
Classifier: Programming Language :: Python :: Implementation :: CPython
Classifier: Programming Language :: Python :: Implementation :: PyPy
Classifier: Topic :: Software Development :: Libraries :: Python Modules
